srgan_krasserm/__init__.py
srgan_krasserm/data.py
srgan_krasserm/train.py
srgan_krasserm/utils.py
srgan_krasserm/model/__init__.py
srgan_krasserm/model/common.py
srgan_krasserm/model/edsr.py
srgan_krasserm/model/srgan.py
srgan_krasserm/model/wdsr.py
srgan_krasserm/weights/srgan/gan_discriminator.h5
srgan_krasserm/weights/srgan/gan_generator.h5
srgan_krasserm/weights/srgan/pre_generator.h5
srgan_krasserm-0.5.dist-info/LICENSE
srgan_krasserm-0.5.dist-info/METADATA
srgan_krasserm-0.5.dist-info/WHEEL
srgan_krasserm-0.5.dist-info/top_level.txt
srgan_krasserm-0.5.dist-info/RECORD
