Metadata-Version: 2.1
Name: srgan-krasserm
Version: 0.5
Summary: Image Scaling
Home-page: UNKNOWN
Author: UNKNOWN
Author-email: UNKNOWN
License: Apache
Platform: UNKNOWN
